[
  {
    "vesselTrackingId": "249981000",
    "timestamp": "2022-03-31T00:01:08",
    "latitude": 29.73634,
    "longitude": -95.05491,
    "speedOverGround": 9.7,
    "courseOverGround": 302.5,
    "heading": 310,
    "vesselName": "SEARANGER",
    "imoNumber": "IMO9759800",
    "navigationStatus": "0"
  },
  {
    "vesselTrackingId": "367662330",
    "timestamp": "2022-03-31T00:00:50",
    "latitude": 38.82952,
    "longitude": -82.15593,
    "speedOverGround": 0,
    "courseOverGround": 287.4,
    "heading": 511,
    "vesselName": "ANDY MULLINS",
    "imoNumber": "",
    "navigationStatus": "0"
  },
  {
    "vesselTrackingId": "338430661",
    "timestamp": "2022-03-31T00:00:53",
    "latitude": 30.29565,
    "longitude": -87.62935,
    "speedOverGround": 0,
    "courseOverGround": 2.3,
    "heading": 511,
    "vesselName": "BASHFUL IV",
    "imoNumber": "IMO0000000",
    "navigationStatus": ""
  },
  {
    "vesselTrackingId": "366841020",
    "timestamp": "2022-03-31T00:01:11",
    "latitude": 29.7088,
    "longitude": -91.21872,
    "speedOverGround": 0,
    "courseOverGround": 19.4,
    "heading": 511,
    "vesselName": "JOSSET",
    "imoNumber": "",
    "navigationStatus": "15"
  },
  {
    "vesselTrackingId": "368175090",
    "timestamp": "2022-03-31T00:00:55",
    "latitude": 27.83867,
    "longitude": -97.06302,
    "speedOverGround": 0,
    "courseOverGround": 177.7,
    "heading": 511,
    "vesselName": "TODO BIEN",
    "imoNumber": "IMO0000000",
    "navigationStatus": ""
  },
  {
    "vesselTrackingId": "366845000",
    "timestamp": "2022-03-31T00:01:12",
    "latitude": 48.10531,
    "longitude": -122.78229,
    "speedOverGround": 0,
    "courseOverGround": 243.4,
    "heading": 511,
    "vesselName": "RAMBLIN ROSE",
    "imoNumber": "IMO8856259",
    "navigationStatus": "0"
  },
  {
    "vesselTrackingId": "367662540",
    "timestamp": "2022-03-31T00:00:56",
    "latitude": 21.31663,
    "longitude": -157.87716,
    "speedOverGround": 0,
    "courseOverGround": 148.2,
    "heading": 511,
    "vesselName": "OKAY",
    "imoNumber": "",
    "navigationStatus": ""
  },
  {
    "vesselTrackingId": "368099990",
    "timestamp": "2022-03-31T00:01:20",
    "latitude": 30.42325,
    "longitude": -91.19544,
    "speedOverGround": 0,
    "courseOverGround": 360,
    "heading": 511,
    "vesselName": "JOHN OLIVER",
    "imoNumber": "",
    "navigationStatus": "0"
  },
  {
    "vesselTrackingId": "368137980",
    "timestamp": "2022-03-31T00:01:14",
    "latitude": 27.8287,
    "longitude": -82.44654,
    "speedOverGround": 9.9,
    "courseOverGround": 6.6,
    "heading": 511,
    "vesselName": "LADY EDWINA",
    "imoNumber": "",
    "navigationStatus": "0"
  },
  {
    "vesselTrackingId": "367458590",
    "timestamp": "2022-03-31T00:01:13",
    "latitude": 33.14565,
    "longitude": -87.69095,
    "speedOverGround": 3.6,
    "courseOverGround": 341.6,
    "heading": 353,
    "vesselName": "TERAH HUCKABEE",
    "imoNumber": "IMO8850970",
    "navigationStatus": "12"
  },
  {
    "vesselTrackingId": "368182060",
    "timestamp": "2022-03-31T00:00:57",
    "latitude": 24.57053,
    "longitude": -81.81355,
    "speedOverGround": 0.1,
    "courseOverGround": 201.8,
    "heading": 104,
    "vesselName": "PYSEAS",
    "imoNumber": "IMO0000000",
    "navigationStatus": ""
  },
  {
    "vesselTrackingId": "367652660",
    "timestamp": "2022-03-31T00:01:24",
    "latitude": 30.25805,
    "longitude": -88.11613,
    "speedOverGround": 0,
    "courseOverGround": 0,
    "heading": 511,
    "vesselName": "FOUR C'S",
    "imoNumber": "",
    "navigationStatus": "0"
  },
  {
    "vesselTrackingId": "3660512",
    "timestamp": "2022-03-31T00:00:44",
    "latitude": 26.12917,
    "longitude": -94.89753,
    "speedOverGround": 0.3,
    "courseOverGround": 204.3,
    "heading": 299,
    "vesselName": "PERDIDO",
    "imoNumber": "",
    "navigationStatus": "1"
  },
  {
    "vesselTrackingId": "368004570",
    "timestamp": "2022-03-31T00:01:02",
    "latitude": 29.72181,
    "longitude": -94.94136,
    "speedOverGround": 0,
    "courseOverGround": 360,
    "heading": 511,
    "vesselName": "HARLAN RICHARDSON",
    "imoNumber": "",
    "navigationStatus": "15"
  },
  {
    "vesselTrackingId": "370375000",
    "timestamp": "2022-03-31T00:01:06",
    "latitude": 25.77299,
    "longitude": -80.17739,
    "speedOverGround": 2.6,
    "courseOverGround": 116.4,
    "heading": 511,
    "vesselName": "LEGEND II",
    "imoNumber": "IMO9376610",
    "navigationStatus": "0"
  },
  {
    "vesselTrackingId": "366953920",
    "timestamp": "2022-03-31T00:01:07",
    "latitude": 36.96214,
    "longitude": -89.09495,
    "speedOverGround": 0,
    "courseOverGround": 346.1,
    "heading": 2,
    "vesselName": "ALICE I HOOKER",
    "imoNumber": "",
    "navigationStatus": "12"
  },
  {
    "vesselTrackingId": "368113990",
    "timestamp": "2022-03-31T00:01:14",
    "latitude": 29.61943,
    "longitude": -89.90993,
    "speedOverGround": 0,
    "courseOverGround": 360,
    "heading": 511,
    "vesselName": "ANDREW S.",
    "imoNumber": "",
    "navigationStatus": "0"
  },
  {
    "vesselTrackingId": "316003289",
    "timestamp": "2022-03-31T00:00:18",
    "latitude": 49.14333,
    "longitude": -123.03603,
    "speedOverGround": 0,
    "courseOverGround": 203.1,
    "heading": 76,
    "vesselName": "PRINCESS SUPERIOR",
    "imoNumber": "IMO7343669",
    "navigationStatus": "0"
  },
  {
    "vesselTrackingId": "372487000",
    "timestamp": "2022-03-31T00:01:02",
    "latitude": 27.36775,
    "longitude": -93.83422,
    "speedOverGround": 13.5,
    "courseOverGround": 121.4,
    "heading": 123,
    "vesselName": "QIAN HAI",
    "imoNumber": "IMO8604979",
    "navigationStatus": "0"
  },
  {
    "vesselTrackingId": "316022036",
    "timestamp": "2022-03-31T00:00:21",
    "latitude": 49.22252,
    "longitude": -122.83985,
    "speedOverGround": 0,
    "courseOverGround": 185.8,
    "heading": 511,
    "vesselName": "QUADRANT WARRIOR",
    "imoNumber": "",
    "navigationStatus": "0"
  },
  {
    "vesselTrackingId": "368223490",
    "timestamp": "2022-03-31T00:01:04",
    "latitude": 26.11582,
    "longitude": -80.10706,
    "speedOverGround": 0.1,
    "courseOverGround": 305.9,
    "heading": 511,
    "vesselName": "POUR VOUS",
    "imoNumber": "",
    "navigationStatus": "0"
  },
  {
    "vesselTrackingId": "538070835",
    "timestamp": "2022-03-31T00:00:21",
    "latitude": 26.75083,
    "longitude": -80.05002,
    "speedOverGround": 0,
    "courseOverGround": 339.9,
    "heading": 101,
    "vesselName": "M4",
    "imoNumber": "",
    "navigationStatus": "12"
  },
  {
    "vesselTrackingId": "367730070",
    "timestamp": "2022-03-31T00:01:05",
    "latitude": 30.41216,
    "longitude": -88.87742,
    "speedOverGround": 0,
    "courseOverGround": 360,
    "heading": 511,
    "vesselName": "LADY JO ANN",
    "imoNumber": "IMO7828906",
    "navigationStatus": ""
  },
  {
    "vesselTrackingId": "367188610",
    "timestamp": "2022-03-31T00:01:11",
    "latitude": 27.94185,
    "longitude": -82.44898,
    "speedOverGround": 0,
    "courseOverGround": 233.3,
    "heading": 511,
    "vesselName": "STARSHIP II",
    "imoNumber": "",
    "navigationStatus": "0"
  },
  {
    "vesselTrackingId": "339822000",
    "timestamp": "2022-03-31T00:00:21",
    "latitude": 26.10272,
    "longitude": -80.11751,
    "speedOverGround": 0,
    "courseOverGround": 204.1,
    "heading": 87,
    "vesselName": "SHE'S A 10",
    "imoNumber": "",
    "navigationStatus": "5"
  },
  {
    "vesselTrackingId": "367645040",
    "timestamp": "2022-03-31T00:01:12",
    "latitude": 30.70844,
    "longitude": -88.04355,
    "speedOverGround": 0,
    "courseOverGround": 299.7,
    "heading": 302,
    "vesselName": "GASPARILLA",
    "imoNumber": "IMO939738900",
    "navigationStatus": "0"
  },
  {
    "vesselTrackingId": "366873510",
    "timestamp": "2022-03-31T00:00:40",
    "latitude": 21.31014,
    "longitude": -157.86586,
    "speedOverGround": 0,
    "courseOverGround": 351.7,
    "heading": 511,
    "vesselName": "AMERICAN CHALLENGER",
    "imoNumber": "IMO7420479",
    "navigationStatus": "5"
  },
  {
    "vesselTrackingId": "367577620",
    "timestamp": "2022-03-31T00:01:16",
    "latitude": 29.74791,
    "longitude": -95.10348,
    "speedOverGround": 1.2,
    "courseOverGround": 253.6,
    "heading": 287,
    "vesselName": "SAVAGE OUTLOOK",
    "imoNumber": "",
    "navigationStatus": "0"
  },
  {
    "vesselTrackingId": "636017075",
    "timestamp": "2022-03-31T00:01:16",
    "latitude": 28.4091,
    "longitude": -80.60634,
    "speedOverGround": 0,
    "courseOverGround": 192.9,
    "heading": 88,
    "vesselName": "DRAWNO",
    "imoNumber": "IMO9727508",
    "navigationStatus": "5"
  },
  {
    "vesselTrackingId": "367446940",
    "timestamp": "2022-03-31T00:00:43",
    "latitude": 29.42807,
    "longitude": -94.61419,
    "speedOverGround": 2.3,
    "courseOverGround": 190.1,
    "heading": 511,
    "vesselName": "GULF SHRIMP",
    "imoNumber": "IMO8034021",
    "navigationStatus": ""
  },
  {
    "vesselTrackingId": "338310483",
    "timestamp": "2022-03-31T00:02:14",
    "latitude": 49.17542,
    "longitude": -122.95749,
    "speedOverGround": 0,
    "courseOverGround": 213.4,
    "heading": 511,
    "vesselName": "SPINNER",
    "imoNumber": "IMO0000000",
    "navigationStatus": ""
  },
  {
    "vesselTrackingId": "367625540",
    "timestamp": "2022-03-31T00:00:46",
    "latitude": 43.83355,
    "longitude": -91.25646,
    "speedOverGround": 0,
    "courseOverGround": 326.5,
    "heading": 511,
    "vesselName": "MEGAN MCB",
    "imoNumber": "",
    "navigationStatus": "15"
  },
  {
    "vesselTrackingId": "636017469",
    "timestamp": "2022-03-31T00:00:53",
    "latitude": 29.99735,
    "longitude": -90.43691,
    "speedOverGround": 0.1,
    "courseOverGround": 191.5,
    "heading": 259,
    "vesselName": "TALIMEN",
    "imoNumber": "IMO9718026",
    "navigationStatus": "1"
  },
  {
    "vesselTrackingId": "367663050",
    "timestamp": "2022-03-31T00:00:54",
    "latitude": 35.67766,
    "longitude": -89.94711,
    "speedOverGround": 0,
    "courseOverGround": 318,
    "heading": 149,
    "vesselName": "BILLY STRAIT",
    "imoNumber": "",
    "navigationStatus": "0"
  },
  {
    "vesselTrackingId": "244674000",
    "timestamp": "2022-03-31T00:01:10",
    "latitude": 29.51327,
    "longitude": -93.22084,
    "speedOverGround": 10.4,
    "courseOverGround": 142.6,
    "heading": 137,
    "vesselName": "MARIETJE DEBORAH",
    "imoNumber": "IMO9481594",
    "navigationStatus": "0"
  },
  {
    "vesselTrackingId": "338922000",
    "timestamp": "2022-03-31T00:01:11",
    "latitude": 47.78462,
    "longitude": -122.45885,
    "speedOverGround": 11,
    "courseOverGround": 166.2,
    "heading": 511,
    "vesselName": "CG HENRY BLAKE",
    "imoNumber": "IMO9177313",
    "navigationStatus": "0"
  },
  {
    "vesselTrackingId": "368205880",
    "timestamp": "2022-03-31T00:01:13",
    "latitude": 29.77907,
    "longitude": -95.10036,
    "speedOverGround": 0,
    "courseOverGround": 218.4,
    "heading": 511,
    "vesselName": "NICHOLAS VETO",
    "imoNumber": "",
    "navigationStatus": "12"
  },
  {
    "vesselTrackingId": "338206764",
    "timestamp": "2022-03-31T00:01:16",
    "latitude": 47.63081,
    "longitude": -122.33982,
    "speedOverGround": 0,
    "courseOverGround": 167.8,
    "heading": 511,
    "vesselName": "UNA VIDA",
    "imoNumber": "",
    "navigationStatus": ""
  },
  {
    "vesselTrackingId": "366997920",
    "timestamp": "2022-03-31T00:01:16",
    "latitude": 28.80782,
    "longitude": -95.54491,
    "speedOverGround": 0,
    "courseOverGround": 55.5,
    "heading": 221,
    "vesselName": "RANDY ECKSTEIN",
    "imoNumber": "IMO8991009",
    "navigationStatus": "12"
  },
  {
    "vesselTrackingId": "368223490",
    "timestamp": "2022-03-31T00:02:15",
    "latitude": 26.11582,
    "longitude": -80.10705,
    "speedOverGround": 0,
    "courseOverGround": 319.2,
    "heading": 511,
    "vesselName": "POUR VOUS",
    "imoNumber": "",
    "navigationStatus": "0"
  },
  {
    "vesselTrackingId": "367050090",
    "timestamp": "2022-03-31T00:01:15",
    "latitude": 40.68888,
    "longitude": -89.5866,
    "speedOverGround": 0,
    "courseOverGround": 202.2,
    "heading": 511,
    "vesselName": "SPIRIT OF PEORIA",
    "imoNumber": "",
    "navigationStatus": "5"
  },
  {
    "vesselTrackingId": "368226810",
    "timestamp": "2022-03-31T00:02:18",
    "latitude": 26.00181,
    "longitude": -80.12206,
    "speedOverGround": 0,
    "courseOverGround": 360,
    "heading": 511,
    "vesselName": "LA VAGABUNDA",
    "imoNumber": "IMO0000000",
    "navigationStatus": ""
  },
  {
    "vesselTrackingId": "366989480",
    "timestamp": "2022-03-31T00:01:14",
    "latitude": 30.34547,
    "longitude": -91.19382,
    "speedOverGround": 13.2,
    "courseOverGround": 71.8,
    "heading": 511,
    "vesselName": "SONNY COOK",
    "imoNumber": "",
    "navigationStatus": "12"
  },
  {
    "vesselTrackingId": "338213453",
    "timestamp": "2022-03-31T00:02:21",
    "latitude": 47.68057,
    "longitude": -122.40695,
    "speedOverGround": 0,
    "courseOverGround": 3,
    "heading": 511,
    "vesselName": "WHITE RABBIT",
    "imoNumber": "IMO0000000",
    "navigationStatus": ""
  },
  {
    "vesselTrackingId": "367645040",
    "timestamp": "2022-03-31T00:02:22",
    "latitude": 30.70843,
    "longitude": -88.04357,
    "speedOverGround": 0,
    "courseOverGround": 104.2,
    "heading": 302,
    "vesselName": "GASPARILLA",
    "imoNumber": "IMO939738900",
    "navigationStatus": "0"
  },
  {
    "vesselTrackingId": "367635370",
    "timestamp": "2022-03-31T00:01:20",
    "latitude": 41.67407,
    "longitude": -87.55216,
    "speedOverGround": 4.6,
    "courseOverGround": 18.8,
    "heading": 511,
    "vesselName": "SYDNEY REESE",
    "imoNumber": "",
    "navigationStatus": "12"
  },
  {
    "vesselTrackingId": "367681460",
    "timestamp": "2022-03-31T00:02:25",
    "latitude": 37.18493,
    "longitude": -89.06405,
    "speedOverGround": 0,
    "courseOverGround": 30.3,
    "heading": 511,
    "vesselName": "ST JAMES",
    "imoNumber": "",
    "navigationStatus": "0"
  },
  {
    "vesselTrackingId": "367374140",
    "timestamp": "2022-03-31T00:01:20",
    "latitude": 29.94082,
    "longitude": -91.84238,
    "speedOverGround": 0,
    "courseOverGround": 156.3,
    "heading": 176,
    "vesselName": "TRINITY",
    "imoNumber": "IMO8943375",
    "navigationStatus": "0"
  },
  {
    "vesselTrackingId": "316001249",
    "timestamp": "2022-03-31T00:01:22",
    "latitude": 49.43386,
    "longitude": -123.45949,
    "speedOverGround": 15.5,
    "courseOverGround": 325.1,
    "heading": 325,
    "vesselName": "QUEEN OF COQUITLAM",
    "imoNumber": "IMO7411155",
    "navigationStatus": "0"
  },
  {
    "vesselTrackingId": "368208150",
    "timestamp": "2022-03-31T00:01:24",
    "latitude": 31.15343,
    "longitude": -81.49994,
    "speedOverGround": 0,
    "courseOverGround": 335.7,
    "heading": 511,
    "vesselName": "CLASSEA",
    "imoNumber": "IMO0000000",
    "navigationStatus": ""
  },
  {
    "vesselTrackingId": "339843000",
    "timestamp": "2022-03-31T00:01:28",
    "latitude": 25.89544,
    "longitude": -80.12879,
    "speedOverGround": 0,
    "courseOverGround": 360,
    "heading": 127,
    "vesselName": "WHITE ROSE",
    "imoNumber": "IMO0000000",
    "navigationStatus": ""
  },
  {
    "vesselTrackingId": "366973450",
    "timestamp": "2022-03-31T00:01:27",
    "latitude": 30.22498,
    "longitude": -93.27743,
    "speedOverGround": 2.2,
    "courseOverGround": 148.3,
    "heading": 511,
    "vesselName": "CAPT LEROY DEVALL",
    "imoNumber": "",
    "navigationStatus": "0"
  },
  {
    "vesselTrackingId": "367017960",
    "timestamp": "2022-03-31T00:01:38",
    "latitude": 29.94805,
    "longitude": -92.70515,
    "speedOverGround": 5.1,
    "courseOverGround": 301.3,
    "heading": 299,
    "vesselName": "CY",
    "imoNumber": "IMO8991023",
    "navigationStatus": "12"
  },
  {
    "vesselTrackingId": "367767850",
    "timestamp": "2022-03-31T00:01:20",
    "latitude": 29.67302,
    "longitude": -89.96367,
    "speedOverGround": 0,
    "courseOverGround": 266.9,
    "heading": 511,
    "vesselName": "BOLD RULER",
    "imoNumber": "",
    "navigationStatus": "15"
  },
  {
    "vesselTrackingId": "367602250",
    "timestamp": "2022-03-31T00:01:11",
    "latitude": 29.77666,
    "longitude": -92.17513,
    "speedOverGround": 0,
    "courseOverGround": 79.2,
    "heading": 298,
    "vesselName": "ADAM JOSEPH",
    "imoNumber": "IMO9579157",
    "navigationStatus": "0"
  },
  {
    "vesselTrackingId": "366992040",
    "timestamp": "2022-03-31T00:01:19",
    "latitude": 29.26348,
    "longitude": -89.35895,
    "speedOverGround": 0,
    "courseOverGround": 257.7,
    "heading": 511,
    "vesselName": "OCEAN PRIDE",
    "imoNumber": "",
    "navigationStatus": "0"
  },
  {
    "vesselTrackingId": "367501370",
    "timestamp": "2022-03-31T00:01:23",
    "latitude": 47.72416,
    "longitude": -122.6405,
    "speedOverGround": 0,
    "courseOverGround": 0,
    "heading": 511,
    "vesselName": "QUE' SA-RAH SA-RAH",
    "imoNumber": "",
    "navigationStatus": ""
  },
  {
    "vesselTrackingId": "368039980",
    "timestamp": "2022-03-31T00:01:12",
    "latitude": 26.83688,
    "longitude": -80.05814,
    "speedOverGround": 0.1,
    "courseOverGround": 256,
    "heading": 511,
    "vesselName": "BOREAS",
    "imoNumber": "",
    "navigationStatus": "0"
  },
  {
    "vesselTrackingId": "368069440",
    "timestamp": "2022-03-31T00:01:35",
    "latitude": 29.25987,
    "longitude": -89.35773,
    "speedOverGround": 0.1,
    "courseOverGround": 234,
    "heading": 511,
    "vesselName": "PORTIER1",
    "imoNumber": "IMO161000000",
    "navigationStatus": "5"
  },
  {
    "vesselTrackingId": "305276000",
    "timestamp": "2022-03-31T00:01:13",
    "latitude": 27.36737,
    "longitude": -94.11382,
    "speedOverGround": 12,
    "courseOverGround": 140.9,
    "heading": 142,
    "vesselName": "BBC RHEIDERLAND",
    "imoNumber": "IMO9614696",
    "navigationStatus": "0"
  },
  {
    "vesselTrackingId": "367609150",
    "timestamp": "2022-03-31T00:01:12",
    "latitude": 30.39051,
    "longitude": -81.48665,
    "speedOverGround": 0,
    "courseOverGround": 243.1,
    "heading": 91,
    "vesselName": "INDIAN DAWN",
    "imoNumber": "IMO7643708",
    "navigationStatus": "0"
  },
  {
    "vesselTrackingId": "368153950",
    "timestamp": "2022-03-31T00:01:34",
    "latitude": 29.94669,
    "longitude": -90.22609,
    "speedOverGround": 0,
    "courseOverGround": 116.4,
    "heading": 252,
    "vesselName": "BROOKE",
    "imoNumber": "IMO0000053",
    "navigationStatus": "0"
  },
  {
    "vesselTrackingId": "367702720",
    "timestamp": "2022-03-31T00:00:32",
    "latitude": 26.10281,
    "longitude": -80.12473,
    "speedOverGround": 0,
    "courseOverGround": 207.2,
    "heading": 511,
    "vesselName": "HAZEL ANN",
    "imoNumber": "",
    "navigationStatus": ""
  },
  {
    "vesselTrackingId": "367440830",
    "timestamp": "2022-03-31T00:01:23",
    "latitude": 29.92524,
    "longitude": -90.13579,
    "speedOverGround": 0,
    "courseOverGround": 92.5,
    "heading": 511,
    "vesselName": "ELIZABETH B",
    "imoNumber": "IMO9585235",
    "navigationStatus": "0"
  },
  {
    "vesselTrackingId": "366963070",
    "timestamp": "2022-03-31T00:00:39",
    "latitude": 37.04082,
    "longitude": -88.53402,
    "speedOverGround": 0,
    "courseOverGround": 259,
    "heading": 145,
    "vesselName": "PHILIP M PFEFFER",
    "imoNumber": "",
    "navigationStatus": "12"
  },
  {
    "vesselTrackingId": "316039252",
    "timestamp": "2022-03-31T00:01:07",
    "latitude": 49.25848,
    "longitude": -125.8699,
    "speedOverGround": 0,
    "courseOverGround": 360,
    "heading": 511,
    "vesselName": "SALAR",
    "imoNumber": "",
    "navigationStatus": "15"
  },
  {
    "vesselTrackingId": "368171310",
    "timestamp": "2022-03-31T00:01:10",
    "latitude": 29.7474,
    "longitude": -95.09859,
    "speedOverGround": 0,
    "courseOverGround": 311,
    "heading": 137,
    "vesselName": "JACK SPERRY",
    "imoNumber": "",
    "navigationStatus": "0"
  },
  {
    "vesselTrackingId": "367505080",
    "timestamp": "2022-03-31T00:01:11",
    "latitude": 28.66863,
    "longitude": -96.00429,
    "speedOverGround": 0.3,
    "courseOverGround": 63.5,
    "heading": 63,
    "vesselName": "CAPT KIRK COLLETTI",
    "imoNumber": "",
    "navigationStatus": "12"
  },
  {
    "vesselTrackingId": "367150170",
    "timestamp": "2022-03-31T00:01:14",
    "latitude": 29.69091,
    "longitude": -91.0983,
    "speedOverGround": 0,
    "courseOverGround": 263.6,
    "heading": 105,
    "vesselName": "CANDY BARREL",
    "imoNumber": "IMO9550929",
    "navigationStatus": "0"
  },
  {
    "vesselTrackingId": "367660390",
    "timestamp": "2022-03-31T00:00:55",
    "latitude": 48.66989,
    "longitude": -123.4066,
    "speedOverGround": 0.1,
    "courseOverGround": 18,
    "heading": 511,
    "vesselName": "FORTY NINER",
    "imoNumber": "",
    "navigationStatus": ""
  },
  {
    "vesselTrackingId": "367755990",
    "timestamp": "2022-03-31T00:01:37",
    "latitude": 29.14622,
    "longitude": -90.19248,
    "speedOverGround": 0,
    "courseOverGround": 266.2,
    "heading": 511,
    "vesselName": "CROSBY DREDGER",
    "imoNumber": "",
    "navigationStatus": "3"
  },
  {
    "vesselTrackingId": "367627770",
    "timestamp": "2022-03-31T00:01:10",
    "latitude": 31.00538,
    "longitude": -91.66336,
    "speedOverGround": 0,
    "courseOverGround": 338.7,
    "heading": 64,
    "vesselName": "KIMBERLY HIDALGO",
    "imoNumber": "",
    "navigationStatus": "12"
  },
  {
    "vesselTrackingId": "316001659",
    "timestamp": "2022-03-31T00:01:40",
    "latitude": 48.4233,
    "longitude": -123.38483,
    "speedOverGround": 0,
    "courseOverGround": 133.4,
    "heading": 511,
    "vesselName": "ZAPORA",
    "imoNumber": "IMO0000000",
    "navigationStatus": ""
  },
  {
    "vesselTrackingId": "366951590",
    "timestamp": "2022-03-31T00:01:11",
    "latitude": 29.31058,
    "longitude": -94.79019,
    "speedOverGround": 0,
    "courseOverGround": 360,
    "heading": 511,
    "vesselName": "CAPT JOHN",
    "imoNumber": "",
    "navigationStatus": "0"
  },
  {
    "vesselTrackingId": "338388816",
    "timestamp": "2022-03-31T00:01:43",
    "latitude": 27.49769,
    "longitude": -82.68574,
    "speedOverGround": 0,
    "courseOverGround": 360,
    "heading": 511,
    "vesselName": "SHE'S THE ONE",
    "imoNumber": "IMO0000000",
    "navigationStatus": ""
  },
  {
    "vesselTrackingId": "367376640",
    "timestamp": "2022-03-31T00:01:14",
    "latitude": 38.4136,
    "longitude": -82.58606,
    "speedOverGround": 0,
    "courseOverGround": 270.6,
    "heading": 137,
    "vesselName": "MAP RUNNER",
    "imoNumber": "",
    "navigationStatus": "0"
  },
  {
    "vesselTrackingId": "368134230",
    "timestamp": "2022-03-31T00:01:54",
    "latitude": 47.63074,
    "longitude": -122.33924,
    "speedOverGround": 0,
    "courseOverGround": 360,
    "heading": 511,
    "vesselName": "LE CANARD",
    "imoNumber": "IMO0000000",
    "navigationStatus": ""
  },
  {
    "vesselTrackingId": "368100220",
    "timestamp": "2022-03-31T00:02:03",
    "latitude": 25.73083,
    "longitude": -80.23131,
    "speedOverGround": 0.2,
    "courseOverGround": 68.4,
    "heading": 511,
    "vesselName": "KAIZEN",
    "imoNumber": "IMO0000000",
    "navigationStatus": ""
  },
  {
    "vesselTrackingId": "366759530",
    "timestamp": "2022-03-31T00:01:13",
    "latitude": 47.26875,
    "longitude": -122.41581,
    "speedOverGround": 0,
    "courseOverGround": 301.5,
    "heading": 320,
    "vesselName": "GUIDE",
    "imoNumber": "IMO9188556",
    "navigationStatus": "0"
  },
  {
    "vesselTrackingId": "367494690",
    "timestamp": "2022-03-31T00:02:05",
    "latitude": 27.94013,
    "longitude": -82.45498,
    "speedOverGround": 0,
    "courseOverGround": 360,
    "heading": 511,
    "vesselName": "LOST PEARL",
    "imoNumber": "IMO0000000",
    "navigationStatus": ""
  },
  {
    "vesselTrackingId": "368010480",
    "timestamp": "2022-03-31T00:01:23",
    "latitude": 30.09043,
    "longitude": -90.91313,
    "speedOverGround": 0.4,
    "courseOverGround": 72.3,
    "heading": 341,
    "vesselName": "CSS GEORGIA",
    "imoNumber": "",
    "navigationStatus": "12"
  },
  {
    "vesselTrackingId": "311000720",
    "timestamp": "2022-03-31T00:02:07",
    "latitude": 17.33534,
    "longitude": -66.20387,
    "speedOverGround": 8.6,
    "courseOverGround": 53.5,
    "heading": 55,
    "vesselName": "CYMBIDIUM",
    "imoNumber": "IMO9781528",
    "navigationStatus": "0"
  },
  {
    "vesselTrackingId": "367701130",
    "timestamp": "2022-03-31T00:01:23",
    "latitude": 43.34648,
    "longitude": -124.32102,
    "speedOverGround": 0.1,
    "courseOverGround": 119.7,
    "heading": 511,
    "vesselName": "CAP ELZA",
    "imoNumber": "",
    "navigationStatus": ""
  },
  {
    "vesselTrackingId": "257020120",
    "timestamp": "2022-03-31T00:02:11",
    "latitude": 18.33456,
    "longitude": -64.95253,
    "speedOverGround": 0,
    "courseOverGround": 204.8,
    "heading": 511,
    "vesselName": "S/Y MARI ANN",
    "imoNumber": "IMO0000000",
    "navigationStatus": ""
  },
  {
    "vesselTrackingId": "229736000",
    "timestamp": "2022-03-31T00:01:01",
    "latitude": 28.97038,
    "longitude": -94.5396,
    "speedOverGround": 0.1,
    "courseOverGround": 150.2,
    "heading": 122,
    "vesselName": "CMA CGM FIGARO",
    "imoNumber": "IMO9450600",
    "navigationStatus": "1"
  },
  {
    "vesselTrackingId": "367666910",
    "timestamp": "2022-03-31T00:01:45",
    "latitude": 29.1439,
    "longitude": -90.20544,
    "speedOverGround": 0,
    "courseOverGround": 271.6,
    "heading": 254,
    "vesselName": "CAJUN IV",
    "imoNumber": "IMO9732761",
    "navigationStatus": "0"
  },
  {
    "vesselTrackingId": "368149130",
    "timestamp": "2022-03-31T00:01:20",
    "latitude": 38.60517,
    "longitude": -90.19161,
    "speedOverGround": 0,
    "courseOverGround": 153.9,
    "heading": 511,
    "vesselName": "TAMMY LYNN",
    "imoNumber": "",
    "navigationStatus": "0"
  },
  {
    "vesselTrackingId": "367633250",
    "timestamp": "2022-03-31T00:02:15",
    "latitude": 30.41623,
    "longitude": -91.20527,
    "speedOverGround": 2.4,
    "courseOverGround": 14.9,
    "heading": 15,
    "vesselName": "LOCKMASTER",
    "imoNumber": "",
    "navigationStatus": "15"
  },
  {
    "vesselTrackingId": "367441370",
    "timestamp": "2022-03-31T00:01:15",
    "latitude": 27.94409,
    "longitude": -82.44221,
    "speedOverGround": 0.1,
    "courseOverGround": 224.7,
    "heading": 511,
    "vesselName": "CROSBY LEADER",
    "imoNumber": "IMO7417288",
    "navigationStatus": "0"
  },
  {
    "vesselTrackingId": "367702510",
    "timestamp": "2022-03-31T00:01:15",
    "latitude": 30.01294,
    "longitude": -90.75791,
    "speedOverGround": 0,
    "courseOverGround": 276.5,
    "heading": 262,
    "vesselName": "SAFETY QUEST",
    "imoNumber": "",
    "navigationStatus": "0"
  },
  {
    "vesselTrackingId": "538070721",
    "timestamp": "2022-03-31T00:01:26",
    "latitude": 18.35719,
    "longitude": -64.58368,
    "speedOverGround": 0.4,
    "courseOverGround": 341.6,
    "heading": 42,
    "vesselName": "SILVER SHALIS",
    "imoNumber": "IMO1010557",
    "navigationStatus": "0"
  },
  {
    "vesselTrackingId": "303999000",
    "timestamp": "2022-03-31T00:01:28",
    "latitude": 21.36606,
    "longitude": -157.96627,
    "speedOverGround": 0,
    "courseOverGround": 0,
    "heading": 511,
    "vesselName": "OSCAR ELTON SETTE",
    "imoNumber": "IMO8835097",
    "navigationStatus": "5"
  },
  {
    "vesselTrackingId": "367709820",
    "timestamp": "2022-03-31T00:01:38",
    "latitude": 41.84708,
    "longitude": -87.65953,
    "speedOverGround": 4.7,
    "courseOverGround": 178.2,
    "heading": 184,
    "vesselName": "NORTHLAND",
    "imoNumber": "",
    "navigationStatus": "0"
  },
  {
    "vesselTrackingId": "366963070",
    "timestamp": "2022-03-31T00:01:50",
    "latitude": 37.04082,
    "longitude": -88.53405,
    "speedOverGround": 0,
    "courseOverGround": 259.7,
    "heading": 145,
    "vesselName": "PHILIP M PFEFFER",
    "imoNumber": "",
    "navigationStatus": "12"
  },
  {
    "vesselTrackingId": "366811310",
    "timestamp": "2022-03-31T00:02:21",
    "latitude": 47.60538,
    "longitude": -122.3701,
    "speedOverGround": 5.8,
    "courseOverGround": 287.7,
    "heading": 284,
    "vesselName": "JAMES T QUIGG",
    "imoNumber": "IMO7129477",
    "navigationStatus": "5"
  },
  {
    "vesselTrackingId": "367528070",
    "timestamp": "2022-03-31T00:01:19",
    "latitude": 28.62072,
    "longitude": -96.1305,
    "speedOverGround": 5.2,
    "courseOverGround": 254.8,
    "heading": 511,
    "vesselName": "MICHELLE ELISE",
    "imoNumber": "",
    "navigationStatus": "12"
  },
  {
    "vesselTrackingId": "366862710",
    "timestamp": "2022-03-31T00:01:36",
    "latitude": 30.10338,
    "longitude": -90.95784,
    "speedOverGround": 0,
    "courseOverGround": 236.9,
    "heading": 264,
    "vesselName": "WALTER E BLESSEY JR",
    "imoNumber": "IMO8976619",
    "navigationStatus": "5"
  },
  {
    "vesselTrackingId": "367482160",
    "timestamp": "2022-03-31T00:02:11",
    "latitude": 47.33061,
    "longitude": -122.57565,
    "speedOverGround": 0.1,
    "courseOverGround": 237.5,
    "heading": 511,
    "vesselName": "GREYWOLF",
    "imoNumber": "",
    "navigationStatus": ""
  },
  {
    "vesselTrackingId": "431148000",
    "timestamp": "2022-03-31T00:01:56",
    "latitude": 29.71005,
    "longitude": -88.26354,
    "speedOverGround": 0,
    "courseOverGround": 209.6,
    "heading": 154,
    "vesselName": "FRONTIER SKY",
    "imoNumber": "IMO9488009",
    "navigationStatus": "1"
  },
  {
    "vesselTrackingId": "218643000",
    "timestamp": "2022-03-31T00:02:17",
    "latitude": 32.82964,
    "longitude": -79.89358,
    "speedOverGround": 0,
    "courseOverGround": 118.8,
    "heading": 21,
    "vesselName": "SANTA LORETTA",
    "imoNumber": "IMO9290567",
    "navigationStatus": "5"
  },
  {
    "vesselTrackingId": "366968740",
    "timestamp": "2022-03-31T00:02:10",
    "latitude": 29.15603,
    "longitude": -89.25663,
    "speedOverGround": 19,
    "courseOverGround": 16.2,
    "heading": 511,
    "vesselName": "NOLA",
    "imoNumber": "",
    "navigationStatus": "15"
  },
  {
    "vesselTrackingId": "367702220",
    "timestamp": "2022-03-31T00:02:21",
    "latitude": 29.78763,
    "longitude": -95.08071,
    "speedOverGround": 0,
    "courseOverGround": 78.1,
    "heading": 341,
    "vesselName": "JOE B WARD",
    "imoNumber": "",
    "navigationStatus": "12"
  },
  {
    "vesselTrackingId": "366772750",
    "timestamp": "2022-03-31T00:02:13",
    "latitude": 48.5896,
    "longitude": -122.92309,
    "speedOverGround": 15.7,
    "courseOverGround": 93.8,
    "heading": 94,
    "vesselName": "WSF YAKIMA",
    "imoNumber": "IMO8835360",
    "navigationStatus": "0"
  },
  {
    "vesselTrackingId": "316033701",
    "timestamp": "2022-03-31T00:02:24",
    "latitude": 49.27372,
    "longitude": -123.13703,
    "speedOverGround": 0.1,
    "courseOverGround": 360,
    "heading": 511,
    "vesselName": "BLUE WATER",
    "imoNumber": "IMO0000000",
    "navigationStatus": ""
  },
  {
    "vesselTrackingId": "367628230",
    "timestamp": "2022-03-31T00:01:47",
    "latitude": 30.52056,
    "longitude": -91.73112,
    "speedOverGround": 0,
    "courseOverGround": 201.3,
    "heading": 328,
    "vesselName": "LAURENCE M GONSOULIN",
    "imoNumber": "",
    "navigationStatus": "0"
  },
  {
    "vesselTrackingId": "368206360",
    "timestamp": "2022-03-31T00:02:22",
    "latitude": 47.6013,
    "longitude": -122.33909,
    "speedOverGround": 0,
    "courseOverGround": 105.2,
    "heading": 57,
    "vesselName": "COMMANDER",
    "imoNumber": "",
    "navigationStatus": "0"
  },
  {
    "vesselTrackingId": "367710540",
    "timestamp": "2022-03-31T00:02:04",
    "latitude": 30.13958,
    "longitude": -90.93539,
    "speedOverGround": 0,
    "courseOverGround": 261.4,
    "heading": 346,
    "vesselName": "AMERICA",
    "imoNumber": "",
    "navigationStatus": "5"
  },
  {
    "vesselTrackingId": "367121850",
    "timestamp": "2022-03-31T00:02:24",
    "latitude": 32.57768,
    "longitude": -91.1191,
    "speedOverGround": 9.6,
    "courseOverGround": 134,
    "heading": 135,
    "vesselName": "LELAND SPEAKES",
    "imoNumber": "",
    "navigationStatus": "15"
  },
  {
    "vesselTrackingId": "367702510",
    "timestamp": "2022-03-31T00:02:16",
    "latitude": 30.01294,
    "longitude": -90.7579,
    "speedOverGround": 0,
    "courseOverGround": 316.3,
    "heading": 261,
    "vesselName": "SAFETY QUEST",
    "imoNumber": "",
    "navigationStatus": "0"
  },
  {
    "vesselTrackingId": "338338944",
    "timestamp": "2022-03-31T00:02:24",
    "latitude": 30.63151,
    "longitude": -81.47733,
    "speedOverGround": 0,
    "courseOverGround": 316.5,
    "heading": 511,
    "vesselName": "KEMO SABE",
    "imoNumber": "IMO0000000",
    "navigationStatus": ""
  },
  {
    "vesselTrackingId": "366921080",
    "timestamp": "2022-03-31T00:02:19",
    "latitude": 29.85124,
    "longitude": -89.98285,
    "speedOverGround": 0.1,
    "courseOverGround": 218,
    "heading": 511,
    "vesselName": "MIRIAM W COOPER",
    "imoNumber": "",
    "navigationStatus": "0"
  },
  {
    "vesselTrackingId": "367673340",
    "timestamp": "2022-03-31T00:02:28",
    "latitude": 30.05493,
    "longitude": -93.7112,
    "speedOverGround": 4.9,
    "courseOverGround": 94.8,
    "heading": 94,
    "vesselName": "J THOMAS",
    "imoNumber": "",
    "navigationStatus": "12"
  },
  {
    "vesselTrackingId": "368090720",
    "timestamp": "2022-03-31T00:01:27",
    "latitude": 29.53579,
    "longitude": -90.78073,
    "speedOverGround": 7.8,
    "courseOverGround": 267.2,
    "heading": 511,
    "vesselName": "ADMIRAL",
    "imoNumber": "",
    "navigationStatus": "0"
  },
  {
    "vesselTrackingId": "368158770",
    "timestamp": "2022-03-31T00:02:28",
    "latitude": 30.40772,
    "longitude": -87.25835,
    "speedOverGround": 0,
    "courseOverGround": 291.8,
    "heading": 293,
    "vesselName": "RIVERS C",
    "imoNumber": "",
    "navigationStatus": "0"
  },
  {
    "vesselTrackingId": "338152277",
    "timestamp": "2022-03-31T00:01:34",
    "latitude": 25.09092,
    "longitude": -80.4348,
    "speedOverGround": 0,
    "courseOverGround": 115,
    "heading": 511,
    "vesselName": "SEAQUEST",
    "imoNumber": "",
    "navigationStatus": ""
  },
  {
    "vesselTrackingId": "367132090",
    "timestamp": "2022-03-31T00:01:47",
    "latitude": 27.69205,
    "longitude": -82.85308,
    "speedOverGround": 2.8,
    "courseOverGround": 137.6,
    "heading": 511,
    "vesselName": "SOUTHERN CROSS",
    "imoNumber": "IMO8885793",
    "navigationStatus": ""
  },
  {
    "vesselTrackingId": "538009901",
    "timestamp": "2022-03-31T00:01:50",
    "latitude": 28.85267,
    "longitude": -90.111,
    "speedOverGround": 0.3,
    "courseOverGround": 173,
    "heading": 203,
    "vesselName": "WEST VELA",
    "imoNumber": "IMO9609407",
    "navigationStatus": "1"
  },
  {
    "vesselTrackingId": "367020820",
    "timestamp": "2022-03-31T00:02:09",
    "latitude": 21.3102,
    "longitude": -157.86589,
    "speedOverGround": 0.1,
    "courseOverGround": 125.1,
    "heading": 263,
    "vesselName": "AMERICAN CHAMPION",
    "imoNumber": "IMO7434016",
    "navigationStatus": "0"
  },
  {
    "vesselTrackingId": "368102350",
    "timestamp": "2022-03-31T00:01:16",
    "latitude": 38.5556,
    "longitude": -90.24139,
    "speedOverGround": 5.7,
    "courseOverGround": 48.4,
    "heading": 511,
    "vesselName": "LEGACY PROVIDER",
    "imoNumber": "",
    "navigationStatus": "0"
  },
  {
    "vesselTrackingId": "316016131",
    "timestamp": "2022-03-31T00:01:14",
    "latitude": 48.41468,
    "longitude": -123.38616,
    "speedOverGround": 0.1,
    "courseOverGround": 155.9,
    "heading": 244,
    "vesselName": "PACIFIC GUARDIAN",
    "imoNumber": "",
    "navigationStatus": "8"
  },
  {
    "vesselTrackingId": "367314660",
    "timestamp": "2022-03-31T00:02:05",
    "latitude": 30.41321,
    "longitude": -88.88029,
    "speedOverGround": 0,
    "courseOverGround": 360,
    "heading": 511,
    "vesselName": "SEA LION VI",
    "imoNumber": "IMO8979996",
    "navigationStatus": ""
  },
  {
    "vesselTrackingId": "367717840",
    "timestamp": "2022-03-31T00:02:14",
    "latitude": 38.40462,
    "longitude": -82.56438,
    "speedOverGround": 1.1,
    "courseOverGround": 113,
    "heading": 511,
    "vesselName": "TAYLOR RENEE",
    "imoNumber": "",
    "navigationStatus": "15"
  },
  {
    "vesselTrackingId": "366951060",
    "timestamp": "2022-03-31T00:00:02",
    "latitude": 36.39607,
    "longitude": -89.5156,
    "speedOverGround": 3.9,
    "courseOverGround": 320.8,
    "heading": 319,
    "vesselName": "AMERICAN HERITAGE",
    "imoNumber": "",
    "navigationStatus": "12"
  },
  {
    "vesselTrackingId": "367582850",
    "timestamp": "2022-03-31T00:02:28",
    "latitude": 27.61128,
    "longitude": -97.25223,
    "speedOverGround": 5.9,
    "courseOverGround": 204.1,
    "heading": 206,
    "vesselName": "CLIFFORD L CARRAWAY",
    "imoNumber": "",
    "navigationStatus": "12"
  },
  {
    "vesselTrackingId": "367598120",
    "timestamp": "2022-03-31T00:01:51",
    "latitude": 29.35577,
    "longitude": -90.25021,
    "speedOverGround": 0.1,
    "courseOverGround": 238.6,
    "heading": 511,
    "vesselName": "GIS-BRAVE",
    "imoNumber": "IMO9184093",
    "navigationStatus": "5"
  },
  {
    "vesselTrackingId": "368204880",
    "timestamp": "2022-03-31T00:02:29",
    "latitude": 18.34196,
    "longitude": -64.79192,
    "speedOverGround": 0,
    "courseOverGround": 360,
    "heading": 511,
    "vesselName": "L' AMITIE",
    "imoNumber": "IMO0000000",
    "navigationStatus": ""
  },
  {
    "vesselTrackingId": "338184205",
    "timestamp": "2022-03-31T00:02:17",
    "latitude": 48.10221,
    "longitude": -122.88404,
    "speedOverGround": 0,
    "courseOverGround": 360,
    "heading": 511,
    "vesselName": "BLUE SNEECH",
    "imoNumber": "",
    "navigationStatus": ""
  },
  {
    "vesselTrackingId": "338401888",
    "timestamp": "2022-03-31T00:02:29",
    "latitude": 47.54071,
    "longitude": -122.64534,
    "speedOverGround": 0,
    "courseOverGround": 360,
    "heading": 511,
    "vesselName": "A BOAT.",
    "imoNumber": "IMO0000000",
    "navigationStatus": ""
  },
  {
    "vesselTrackingId": "367532880",
    "timestamp": "2022-03-31T00:02:21",
    "latitude": 38.53869,
    "longitude": -90.25051,
    "speedOverGround": 0,
    "courseOverGround": 360,
    "heading": 511,
    "vesselName": "EVA WALKER",
    "imoNumber": "IMO8842313",
    "navigationStatus": "0"
  },
  {
    "vesselTrackingId": "338361406",
    "timestamp": "2022-03-31T00:02:29",
    "latitude": 27.74512,
    "longitude": -82.7213,
    "speedOverGround": 0,
    "courseOverGround": 360,
    "heading": 511,
    "vesselName": "CADDYSHACK",
    "imoNumber": "IMO0000000",
    "navigationStatus": ""
  },
  {
    "vesselTrackingId": "319208100",
    "timestamp": "2022-03-31T00:02:32",
    "latitude": 26.38899,
    "longitude": -80.07294,
    "speedOverGround": 0,
    "courseOverGround": 360,
    "heading": 511,
    "vesselName": "SILENCE",
    "imoNumber": "IMO0000000",
    "navigationStatus": ""
  },
  {
    "vesselTrackingId": "367684360",
    "timestamp": "2022-03-31T00:02:24",
    "latitude": 38.75216,
    "longitude": -85.03302,
    "speedOverGround": 0.4,
    "courseOverGround": 209.7,
    "heading": 511,
    "vesselName": "J L BRADEN",
    "imoNumber": "",
    "navigationStatus": "0"
  },
  {
    "vesselTrackingId": "338390857",
    "timestamp": "2022-03-31T00:02:34",
    "latitude": 47.64202,
    "longitude": -122.3424,
    "speedOverGround": 0,
    "courseOverGround": 4.8,
    "heading": 511,
    "vesselName": "AGLAIA",
    "imoNumber": "IMO0000000",
    "navigationStatus": ""
  },
  {
    "vesselTrackingId": "366972620",
    "timestamp": "2022-03-31T00:02:24",
    "latitude": 21.31027,
    "longitude": -157.86926,
    "speedOverGround": 0,
    "courseOverGround": 128.8,
    "heading": 511,
    "vesselName": "MIKIOI",
    "imoNumber": "IMO8987723",
    "navigationStatus": "0"
  },
  {
    "vesselTrackingId": "367560990",
    "timestamp": "2022-03-31T00:02:39",
    "latitude": 27.63562,
    "longitude": -82.56339,
    "speedOverGround": 0,
    "courseOverGround": 299.3,
    "heading": 174,
    "vesselName": "ATLAS",
    "imoNumber": "IMO9641754",
    "navigationStatus": "0"
  },
  {
    "vesselTrackingId": "367093690",
    "timestamp": "2022-03-31T00:00:10",
    "latitude": 30.86222,
    "longitude": -91.81411,
    "speedOverGround": 0,
    "courseOverGround": 241.9,
    "heading": 511,
    "vesselName": "MISS NINA",
    "imoNumber": "",
    "navigationStatus": "0"
  },
  {
    "vesselTrackingId": "319304000",
    "timestamp": "2022-03-31T00:02:14",
    "latitude": 26.75028,
    "longitude": -80.05081,
    "speedOverGround": 0,
    "courseOverGround": 0,
    "heading": 93,
    "vesselName": "MADSUMMER",
    "imoNumber": "IMO1008413",
    "navigationStatus": "5"
  },
  {
    "vesselTrackingId": "367561870",
    "timestamp": "2022-03-31T00:02:21",
    "latitude": 30.03526,
    "longitude": -90.83768,
    "speedOverGround": 8.3,
    "courseOverGround": 173.3,
    "heading": 174,
    "vesselName": "SAVAGE DESTINY",
    "imoNumber": "",
    "navigationStatus": "12"
  },
  {
    "vesselTrackingId": "368157160",
    "timestamp": "2022-03-31T00:02:24",
    "latitude": 32.08799,
    "longitude": -81.06247,
    "speedOverGround": 0.1,
    "courseOverGround": 133,
    "heading": 511,
    "vesselName": "MISS DOT G",
    "imoNumber": "",
    "navigationStatus": "0"
  },
  {
    "vesselTrackingId": "538070791",
    "timestamp": "2022-03-31T00:02:31",
    "latitude": 17.66795,
    "longitude": -67.43882,
    "speedOverGround": 10.6,
    "courseOverGround": 264,
    "heading": 260,
    "vesselName": "SOFIA 3",
    "imoNumber": "IMO9507283",
    "navigationStatus": "0"
  },
  {
    "vesselTrackingId": "538070791",
    "timestamp": "2022-03-31T00:01:20",
    "latitude": 17.66825,
    "longitude": -67.43523,
    "speedOverGround": 10.6,
    "courseOverGround": 262.6,
    "heading": 263,
    "vesselName": "SOFIA 3",
    "imoNumber": "IMO9507283",
    "navigationStatus": "0"
  },
  {
    "vesselTrackingId": "368242390",
    "timestamp": "2022-03-31T00:02:17",
    "latitude": 30.01978,
    "longitude": -94.02492,
    "speedOverGround": 0,
    "courseOverGround": 250.3,
    "heading": 297,
    "vesselName": "OLD HICKORY",
    "imoNumber": "",
    "navigationStatus": "0"
  },
  {
    "vesselTrackingId": "366996340",
    "timestamp": "2022-03-31T00:02:21",
    "latitude": 30.06957,
    "longitude": -94.04841,
    "speedOverGround": 0,
    "courseOverGround": 300.1,
    "heading": 511,
    "vesselName": "PALO DURO",
    "imoNumber": "",
    "navigationStatus": "0"
  },
  {
    "vesselTrackingId": "367629050",
    "timestamp": "2022-03-31T00:02:41",
    "latitude": 26.08563,
    "longitude": -80.19444,
    "speedOverGround": 0,
    "courseOverGround": 68.6,
    "heading": 511,
    "vesselName": "LAUDERDALE LADY",
    "imoNumber": "IMO0000000",
    "navigationStatus": ""
  },
  {
    "vesselTrackingId": "518101002",
    "timestamp": "2022-03-31T00:02:44",
    "latitude": 26.09688,
    "longitude": -80.16165,
    "speedOverGround": 0.1,
    "courseOverGround": 183.1,
    "heading": 93,
    "vesselName": "MARIA THERESA",
    "imoNumber": "IMO0000000",
    "navigationStatus": ""
  },
  {
    "vesselTrackingId": "319026600",
    "timestamp": "2022-03-31T00:02:23",
    "latitude": 26.09778,
    "longitude": -80.16316,
    "speedOverGround": 0.1,
    "courseOverGround": 313.2,
    "heading": 86,
    "vesselName": "CHIQUI",
    "imoNumber": "",
    "navigationStatus": "0"
  },
  {
    "vesselTrackingId": "368039730",
    "timestamp": "2022-03-31T00:02:20",
    "latitude": 30.03425,
    "longitude": -90.68626,
    "speedOverGround": 0,
    "courseOverGround": 249.9,
    "heading": 511,
    "vesselName": "LOUISIANA SKY",
    "imoNumber": "",
    "navigationStatus": "0"
  },
  {
    "vesselTrackingId": "367598280",
    "timestamp": "2022-03-31T00:02:23",
    "latitude": 26.05485,
    "longitude": -97.21259,
    "speedOverGround": 0,
    "courseOverGround": 304.2,
    "heading": 511,
    "vesselName": "MISS BETH",
    "imoNumber": "",
    "navigationStatus": "15"
  },
  {
    "vesselTrackingId": "367652850",
    "timestamp": "2022-03-31T00:01:01",
    "latitude": 26.70176,
    "longitude": -80.04476,
    "speedOverGround": 0,
    "courseOverGround": 341.6,
    "heading": 511,
    "vesselName": "RESILIENT",
    "imoNumber": "",
    "navigationStatus": ""
  },
  {
    "vesselTrackingId": "316026464",
    "timestamp": "2022-03-31T00:01:08",
    "latitude": 49.24994,
    "longitude": -123.26457,
    "speedOverGround": 0.8,
    "courseOverGround": 161.3,
    "heading": 234,
    "vesselName": "RIVER STAR",
    "imoNumber": "",
    "navigationStatus": "0"
  },
  {
    "vesselTrackingId": "366972620",
    "timestamp": "2022-03-31T00:01:13",
    "latitude": 21.31028,
    "longitude": -157.86925,
    "speedOverGround": 0.1,
    "courseOverGround": 125.5,
    "heading": 511,
    "vesselName": "MIKIOI",
    "imoNumber": "IMO8987723",
    "navigationStatus": "0"
  },
  {
    "vesselTrackingId": "367578080",
    "timestamp": "2022-03-31T00:02:52",
    "latitude": 29.53568,
    "longitude": -90.79093,
    "speedOverGround": 4,
    "courseOverGround": 100.7,
    "heading": 98,
    "vesselName": "MISS DANIELLE",
    "imoNumber": "",
    "navigationStatus": "0"
  },
  {
    "vesselTrackingId": "311000807",
    "timestamp": "2022-03-31T00:01:21",
    "latitude": 23.78913,
    "longitude": -81.96042,
    "speedOverGround": 17.7,
    "courseOverGround": 71.7,
    "heading": 80,
    "vesselName": "SCARLET LADY",
    "imoNumber": "IMO9804801",
    "navigationStatus": "0"
  },
  {
    "vesselTrackingId": "368159550",
    "timestamp": "2022-03-31T00:02:54",
    "latitude": 26.11918,
    "longitude": -80.14716,
    "speedOverGround": 0,
    "courseOverGround": 151.7,
    "heading": 511,
    "vesselName": "SHINGITAI",
    "imoNumber": "IMO0000000",
    "navigationStatus": ""
  },
  {
    "vesselTrackingId": "367493000",
    "timestamp": "2022-03-31T00:01:13",
    "latitude": 32.70519,
    "longitude": -79.77145,
    "speedOverGround": 2,
    "courseOverGround": 297.2,
    "heading": 295,
    "vesselName": "DOUGLAS B.MACKIE",
    "imoNumber": "IMO9807073",
    "navigationStatus": "3"
  },
  {
    "vesselTrackingId": "316011746",
    "timestamp": "2022-03-31T00:03:00",
    "latitude": 49.22142,
    "longitude": -122.88853,
    "speedOverGround": 0,
    "courseOverGround": 233.6,
    "heading": 511,
    "vesselName": "SEA IMP XII",
    "imoNumber": "",
    "navigationStatus": "0"
  },
  {
    "vesselTrackingId": "367772070",
    "timestamp": "2022-03-31T00:01:29",
    "latitude": 47.6781,
    "longitude": -122.40895,
    "speedOverGround": 0,
    "courseOverGround": 0.6,
    "heading": 511,
    "vesselName": "MERLIN",
    "imoNumber": "",
    "navigationStatus": ""
  },
  {
    "vesselTrackingId": "367538940",
    "timestamp": "2022-03-31T00:01:29",
    "latitude": 29.57678,
    "longitude": -90.60572,
    "speedOverGround": 0.1,
    "courseOverGround": 176.4,
    "heading": 511,
    "vesselName": "RITA ANN",
    "imoNumber": "",
    "navigationStatus": "0"
  },
  {
    "vesselTrackingId": "368047610",
    "timestamp": "2022-03-31T00:01:39",
    "latitude": 37.03612,
    "longitude": -88.44501,
    "speedOverGround": 0,
    "courseOverGround": 360,
    "heading": 511,
    "vesselName": "KEN ECHOLS",
    "imoNumber": "",
    "navigationStatus": "0"
  },
  {
    "vesselTrackingId": "367778560",
    "timestamp": "2022-03-31T00:01:44",
    "latitude": 40.47401,
    "longitude": -80.04514,
    "speedOverGround": 0,
    "courseOverGround": 360,
    "heading": 511,
    "vesselName": "ATB READSHAW",
    "imoNumber": "",
    "navigationStatus": "5"
  },
  {
    "vesselTrackingId": "366988190",
    "timestamp": "2022-03-31T00:01:46",
    "latitude": 41.82753,
    "longitude": -90.19015,
    "speedOverGround": 0,
    "courseOverGround": 258,
    "heading": 54,
    "vesselName": "PRAIRIE DAWN",
    "imoNumber": "IMO8332447",
    "navigationStatus": "12"
  },
  {
    "vesselTrackingId": "367685610",
    "timestamp": "2022-03-31T00:02:09",
    "latitude": 38.98832,
    "longitude": -81.93746,
    "speedOverGround": 0,
    "courseOverGround": 360,
    "heading": 511,
    "vesselName": "MR KING",
    "imoNumber": "",
    "navigationStatus": "0"
  },
  {
    "vesselTrackingId": "367309870",
    "timestamp": "2022-03-31T00:01:01",
    "latitude": 21.31079,
    "longitude": -157.86532,
    "speedOverGround": 0,
    "courseOverGround": 141.9,
    "heading": 511,
    "vesselName": "NENE",
    "imoNumber": "",
    "navigationStatus": "5"
  },
  {
    "vesselTrackingId": "367156710",
    "timestamp": "2022-03-31T00:02:19",
    "latitude": 29.13774,
    "longitude": -89.24829,
    "speedOverGround": 0,
    "courseOverGround": 232.9,
    "heading": 511,
    "vesselName": "JOAN CENAC",
    "imoNumber": "",
    "navigationStatus": "8"
  },
  {
    "vesselTrackingId": "367481590",
    "timestamp": "2022-03-31T00:01:19",
    "latitude": 38.18786,
    "longitude": -90.32837,
    "speedOverGround": 0.1,
    "courseOverGround": 216.4,
    "heading": 511,
    "vesselName": "ERNIE T WELLHAUSEN",
    "imoNumber": "",
    "navigationStatus": "0"
  },
  {
    "vesselTrackingId": "367185050",
    "timestamp": "2022-03-31T00:01:12",
    "latitude": 43.71384,
    "longitude": -124.10174,
    "speedOverGround": 0,
    "courseOverGround": 286.3,
    "heading": 511,
    "vesselName": "SEA VENTURE",
    "imoNumber": "IMO7019232",
    "navigationStatus": "0"
  },
  {
    "vesselTrackingId": "316026565",
    "timestamp": "2022-03-31T00:01:32",
    "latitude": 48.51301,
    "longitude": -122.60868,
    "speedOverGround": 0,
    "courseOverGround": 209.4,
    "heading": 511,
    "vesselName": "LOLANI",
    "imoNumber": "",
    "navigationStatus": ""
  },
  {
    "vesselTrackingId": "367433620",
    "timestamp": "2022-03-31T00:02:06",
    "latitude": 36.96278,
    "longitude": -89.0949,
    "speedOverGround": 0,
    "courseOverGround": 272.3,
    "heading": 511,
    "vesselName": "LLOYD DUNNING",
    "imoNumber": "IMO7207724",
    "navigationStatus": "15"
  },
  {
    "vesselTrackingId": "367471360",
    "timestamp": "2022-03-31T00:02:07",
    "latitude": 35.94276,
    "longitude": -89.68661,
    "speedOverGround": 0,
    "courseOverGround": 360,
    "heading": 511,
    "vesselName": "AUSTIN STONE",
    "imoNumber": "",
    "navigationStatus": "0"
  },
  {
    "vesselTrackingId": "316026464",
    "timestamp": "2022-03-31T00:02:15",
    "latitude": 49.24963,
    "longitude": -123.26445,
    "speedOverGround": 0.9,
    "courseOverGround": 163,
    "heading": 249,
    "vesselName": "RIVER STAR",
    "imoNumber": "",
    "navigationStatus": "0"
  },
  {
    "vesselTrackingId": "369970443",
    "timestamp": "2022-03-31T00:01:14",
    "latitude": 41.42583,
    "longitude": -91.00893,
    "speedOverGround": 0,
    "courseOverGround": 276.1,
    "heading": 511,
    "vesselName": "ROCK ISLAND",
    "imoNumber": "",
    "navigationStatus": "12"
  },
  {
    "vesselTrackingId": "316022028",
    "timestamp": "2022-03-31T00:03:05",
    "latitude": 48.8542,
    "longitude": -123.49876,
    "speedOverGround": 0,
    "courseOverGround": 360,
    "heading": 105,
    "vesselName": "CAPTAIN JACK",
    "imoNumber": "IMO0000000",
    "navigationStatus": ""
  },
  {
    "vesselTrackingId": "368006000",
    "timestamp": "2022-03-31T00:01:14",
    "latitude": 21.35291,
    "longitude": -157.94799,
    "speedOverGround": 0,
    "courseOverGround": 84.1,
    "heading": 511,
    "vesselName": "SHOUP",
    "imoNumber": "",
    "navigationStatus": "0"
  },
  {
    "vesselTrackingId": "373592000",
    "timestamp": "2022-03-31T00:01:47",
    "latitude": 27.82487,
    "longitude": -96.94906,
    "speedOverGround": 0.1,
    "courseOverGround": 10.9,
    "heading": 9,
    "vesselName": "IRENE A",
    "imoNumber": "IMO9870513",
    "navigationStatus": "1"
  },
  {
    "vesselTrackingId": "368112680",
    "timestamp": "2022-03-31T00:00:33",
    "latitude": 27.36986,
    "longitude": -82.6179,
    "speedOverGround": 0,
    "courseOverGround": 13.9,
    "heading": 511,
    "vesselName": "SERENDIPITY",
    "imoNumber": "IMO0000000",
    "navigationStatus": ""
  },
  {
    "vesselTrackingId": "367474790",
    "timestamp": "2022-03-31T00:00:16",
    "latitude": 30.09889,
    "longitude": -93.31509,
    "speedOverGround": 0.5,
    "courseOverGround": 31.2,
    "heading": 511,
    "vesselName": "CROSBY PROGRESS",
    "imoNumber": "IMO8991712",
    "navigationStatus": "0"
  },
  {
    "vesselTrackingId": "367733950",
    "timestamp": "2022-03-31T00:00:40",
    "latitude": 48.51425,
    "longitude": -122.60532,
    "speedOverGround": 0,
    "courseOverGround": 116.3,
    "heading": 270,
    "vesselName": "INVICTUS",
    "imoNumber": "IMO0000000",
    "navigationStatus": ""
  },
  {
    "vesselTrackingId": "366772760",
    "timestamp": "2022-03-31T00:02:24",
    "latitude": 47.61996,
    "longitude": -122.51312,
    "speedOverGround": 0,
    "courseOverGround": 293.5,
    "heading": 293,
    "vesselName": "WSF TACOMA",
    "imoNumber": "IMO9133977",
    "navigationStatus": "0"
  },
  {
    "vesselTrackingId": "367739340",
    "timestamp": "2022-03-31T00:00:50",
    "latitude": 30.27311,
    "longitude": -81.71813,
    "speedOverGround": 0,
    "courseOverGround": 342.9,
    "heading": 43,
    "vesselName": "PLANE 2 SEA",
    "imoNumber": "",
    "navigationStatus": ""
  },
  {
    "vesselTrackingId": "367656670",
    "timestamp": "2022-03-31T00:00:59",
    "latitude": 30.05889,
    "longitude": -93.3551,
    "speedOverGround": 0,
    "courseOverGround": 153.4,
    "heading": 164,
    "vesselName": "GENIE CENAC",
    "imoNumber": "",
    "navigationStatus": "5"
  },
  {
    "vesselTrackingId": "316047565",
    "timestamp": "2022-03-31T00:01:07",
    "latitude": 48.74767,
    "longitude": -123.34293,
    "speedOverGround": 16.4,
    "courseOverGround": 182.9,
    "heading": 183,
    "vesselName": "SEASPAN TRADER",
    "imoNumber": "IMO9886392",
    "navigationStatus": "0"
  },
  {
    "vesselTrackingId": "368214170",
    "timestamp": "2022-03-31T00:01:10",
    "latitude": 27.81574,
    "longitude": -97.42199,
    "speedOverGround": 0,
    "courseOverGround": 311.3,
    "heading": 292,
    "vesselName": "BUD GOLDING",
    "imoNumber": "",
    "navigationStatus": "0"
  },
  {
    "vesselTrackingId": "367378280",
    "timestamp": "2022-03-31T00:01:10",
    "latitude": 37.94339,
    "longitude": -87.41733,
    "speedOverGround": 5.3,
    "courseOverGround": 94.2,
    "heading": 101,
    "vesselName": "ARNOLD W MULZER",
    "imoNumber": "",
    "navigationStatus": "12"
  },
  {
    "vesselTrackingId": "367513230",
    "timestamp": "2022-03-31T00:01:12",
    "latitude": 45.64097,
    "longitude": -122.72327,
    "speedOverGround": 4.1,
    "courseOverGround": 114.8,
    "heading": 114,
    "vesselName": "WILLAMETTE",
    "imoNumber": "IMO8972998",
    "navigationStatus": "0"
  },
  {
    "vesselTrackingId": "366983460",
    "timestamp": "2022-03-31T00:01:15",
    "latitude": 30.05411,
    "longitude": -90.56876,
    "speedOverGround": 0,
    "courseOverGround": 0,
    "heading": 511,
    "vesselName": "MISSISSIPPI",
    "imoNumber": "",
    "navigationStatus": "5"
  },
  {
    "vesselTrackingId": "367343230",
    "timestamp": "2022-03-31T00:01:17",
    "latitude": 26.08245,
    "longitude": -80.11612,
    "speedOverGround": 0,
    "courseOverGround": 360,
    "heading": 264,
    "vesselName": "ST JOHNS",
    "imoNumber": "IMO9188180",
    "navigationStatus": "0"
  },
  {
    "vesselTrackingId": "368212210",
    "timestamp": "2022-03-31T00:01:17",
    "latitude": 29.46645,
    "longitude": -94.96962,
    "speedOverGround": 0,
    "courseOverGround": 306.5,
    "heading": 511,
    "vesselName": "GRADY RAY",
    "imoNumber": "IMO8891493",
    "navigationStatus": "15"
  },
  {
    "vesselTrackingId": "563076900",
    "timestamp": "2022-03-31T00:01:25",
    "latitude": 49.19964,
    "longitude": -123.90581,
    "speedOverGround": 0.1,
    "courseOverGround": 46,
    "heading": 4,
    "vesselName": "CEMTEX DILIGENCE",
    "imoNumber": "IMO9820673",
    "navigationStatus": "1"
  },
  {
    "vesselTrackingId": "538070463",
    "timestamp": "2022-03-31T00:01:26",
    "latitude": 26.74883,
    "longitude": -80.05044,
    "speedOverGround": 0,
    "courseOverGround": 260,
    "heading": 183,
    "vesselName": "STAMPEDE",
    "imoNumber": "",
    "navigationStatus": "5"
  },
  {
    "vesselTrackingId": "367548230",
    "timestamp": "2022-03-31T00:01:22",
    "latitude": 29.96555,
    "longitude": -90.27271,
    "speedOverGround": 5.3,
    "courseOverGround": 261.3,
    "heading": 511,
    "vesselName": "LOUISIANA PRIDE",
    "imoNumber": "",
    "navigationStatus": "0"
  },
  {
    "vesselTrackingId": "367665370",
    "timestamp": "2022-03-31T00:01:28",
    "latitude": 37.05328,
    "longitude": -88.39579,
    "speedOverGround": 0,
    "courseOverGround": 360,
    "heading": 511,
    "vesselName": "GEORGE LEAVELL",
    "imoNumber": "",
    "navigationStatus": "0"
  },
  {
    "vesselTrackingId": "378112323",
    "timestamp": "2022-03-31T00:01:31",
    "latitude": 26.09791,
    "longitude": -80.16321,
    "speedOverGround": 0,
    "courseOverGround": 259.3,
    "heading": 91,
    "vesselName": "ALEGRIA",
    "imoNumber": "IMO9579171",
    "navigationStatus": "5"
  },
  {
    "vesselTrackingId": "367443920",
    "timestamp": "2022-03-31T00:00:28",
    "latitude": 29.99284,
    "longitude": -90.82581,
    "speedOverGround": 0,
    "courseOverGround": 225.8,
    "heading": 337,
    "vesselName": "JOHN 3:16",
    "imoNumber": "IMO8975835",
    "navigationStatus": "12"
  },
  {
    "vesselTrackingId": "636011285",
    "timestamp": "2022-03-31T00:01:35",
    "latitude": 26.09076,
    "longitude": -80.12023,
    "speedOverGround": 0,
    "courseOverGround": 266.2,
    "heading": 267,
    "vesselName": "LISSA TOPIC",
    "imoNumber": "IMO9251327",
    "navigationStatus": "5"
  },
  {
    "vesselTrackingId": "367595460",
    "timestamp": "2022-03-31T00:02:08",
    "latitude": 41.41542,
    "longitude": -88.21076,
    "speedOverGround": 0,
    "courseOverGround": 276.5,
    "heading": 241,
    "vesselName": "THREE RIVERS",
    "imoNumber": "",
    "navigationStatus": "12"
  },
  {
    "vesselTrackingId": "367340160",
    "timestamp": "2022-03-31T00:01:35",
    "latitude": 29.64018,
    "longitude": -91.11152,
    "speedOverGround": 0,
    "courseOverGround": 105.6,
    "heading": 511,
    "vesselName": "CAROLINA",
    "imoNumber": "IMO0552707",
    "navigationStatus": "5"
  },
  {
    "vesselTrackingId": "368072130",
    "timestamp": "2022-03-31T00:02:22",
    "latitude": 27.72475,
    "longitude": -82.68325,
    "speedOverGround": 102.3,
    "courseOverGround": 360,
    "heading": 511,
    "vesselName": "JOURNEY ON",
    "imoNumber": "",
    "navigationStatus": "11"
  },
  {
    "vesselTrackingId": "338167019",
    "timestamp": "2022-03-31T00:02:03",
    "latitude": 47.26303,
    "longitude": -122.35932,
    "speedOverGround": 0.1,
    "courseOverGround": 25.3,
    "heading": 511,
    "vesselName": "BERINY",
    "imoNumber": "",
    "navigationStatus": ""
  },
  {
    "vesselTrackingId": "369564000",
    "timestamp": "2022-03-31T00:02:24",
    "latitude": 30.7075,
    "longitude": -88.04368,
    "speedOverGround": 0,
    "courseOverGround": 127.1,
    "heading": 296,
    "vesselName": "APOLLO",
    "imoNumber": "IMO9703289",
    "navigationStatus": "0"
  },
  {
    "vesselTrackingId": "366999524",
    "timestamp": "2022-03-31T00:01:36",
    "latitude": 31.54368,
    "longitude": -91.43443,
    "speedOverGround": 0,
    "courseOverGround": 6.9,
    "heading": 101,
    "vesselName": "CG GREENBRIER",
    "imoNumber": "",
    "navigationStatus": "3"
  },
  {
    "vesselTrackingId": "316005998",
    "timestamp": "2022-03-31T00:01:21",
    "latitude": 49.29134,
    "longitude": -123.0584,
    "speedOverGround": 0,
    "courseOverGround": 226.4,
    "heading": 57,
    "vesselName": "OSPREY NO 1",
    "imoNumber": "IMO9158173",
    "navigationStatus": "7"
  },
  {
    "vesselTrackingId": "366967580",
    "timestamp": "2022-03-31T00:01:55",
    "latitude": 41.31925,
    "longitude": -88.96241,
    "speedOverGround": 4.2,
    "courseOverGround": 279.7,
    "heading": 280,
    "vesselName": "ERNA E HONEYCUTT",
    "imoNumber": "",
    "navigationStatus": "12"
  },
  {
    "vesselTrackingId": "257532000",
    "timestamp": "2022-03-31T00:01:58",
    "latitude": 48.82769,
    "longitude": -123.43106,
    "speedOverGround": 0.5,
    "courseOverGround": 170,
    "heading": 247,
    "vesselName": "STAR ISMENE",
    "imoNumber": "IMO9182966",
    "navigationStatus": "1"
  },
  {
    "vesselTrackingId": "367033570",
    "timestamp": "2022-03-31T00:02:16",
    "latitude": 29.4009,
    "longitude": -89.26533,
    "speedOverGround": 0.1,
    "courseOverGround": 10.7,
    "heading": 511,
    "vesselName": "EMILY ARIEL",
    "imoNumber": "IMO8958083",
    "navigationStatus": ""
  },
  {
    "vesselTrackingId": "366341000",
    "timestamp": "2022-03-31T00:02:21",
    "latitude": 45.56769,
    "longitude": -122.71951,
    "speedOverGround": 0,
    "courseOverGround": 122.1,
    "heading": 127,
    "vesselName": "PRIDE",
    "imoNumber": "IMO9369423",
    "navigationStatus": "0"
  },
  {
    "vesselTrackingId": "368127980",
    "timestamp": "2022-03-31T00:02:20",
    "latitude": 26.08219,
    "longitude": -80.11627,
    "speedOverGround": 0,
    "courseOverGround": 309.5,
    "heading": 511,
    "vesselName": "EILEEN MCALLISTER",
    "imoNumber": "IMO9903592",
    "navigationStatus": "0"
  },
  {
    "vesselTrackingId": "366963830",
    "timestamp": "2022-03-31T00:02:21",
    "latitude": 30.12895,
    "longitude": -91.01964,
    "speedOverGround": 9.1,
    "courseOverGround": 265.8,
    "heading": 511,
    "vesselName": "SHELLEY",
    "imoNumber": "",
    "navigationStatus": "0"
  },
  {
    "vesselTrackingId": "366998890",
    "timestamp": "2022-03-31T00:02:25",
    "latitude": 29.99618,
    "longitude": -93.94743,
    "speedOverGround": 0,
    "courseOverGround": 268.2,
    "heading": 511,
    "vesselName": "APACHE",
    "imoNumber": "",
    "navigationStatus": "0"
  },
  {
    "vesselTrackingId": "367666850",
    "timestamp": "2022-03-31T00:02:15",
    "latitude": 41.70473,
    "longitude": -87.5458,
    "speedOverGround": 3.5,
    "courseOverGround": 173.3,
    "heading": 184,
    "vesselName": "SARAH ANDRIE",
    "imoNumber": "IMO7114032",
    "navigationStatus": "0"
  },
  {
    "vesselTrackingId": "367414110",
    "timestamp": "2022-03-31T00:02:16",
    "latitude": 39.22727,
    "longitude": -81.69087,
    "speedOverGround": 5.9,
    "courseOverGround": 199.4,
    "heading": 214,
    "vesselName": "FINDLAY",
    "imoNumber": "",
    "navigationStatus": "12"
  },
  {
    "vesselTrackingId": "367116620",
    "timestamp": "2022-03-31T00:02:18",
    "latitude": 29.3953,
    "longitude": -92.22862,
    "speedOverGround": 0.6,
    "courseOverGround": 218.8,
    "heading": 511,
    "vesselName": "ST MICHAEL II",
    "imoNumber": "IMO8976970",
    "navigationStatus": ""
  },
  {
    "vesselTrackingId": "367530230",
    "timestamp": "2022-03-31T00:02:22",
    "latitude": 35.3482,
    "longitude": -94.7778,
    "speedOverGround": 0,
    "courseOverGround": 61.9,
    "heading": 511,
    "vesselName": "BRUCE OAKLEY",
    "imoNumber": "",
    "navigationStatus": "15"
  },
  {
    "vesselTrackingId": "367637960",
    "timestamp": "2022-03-31T00:02:19",
    "latitude": 30.07635,
    "longitude": -90.90902,
    "speedOverGround": 0.1,
    "courseOverGround": 360,
    "heading": 511,
    "vesselName": "JOHN PAUL ECKSTEIN",
    "imoNumber": "",
    "navigationStatus": "12"
  },
  {
    "vesselTrackingId": "368102380",
    "timestamp": "2022-03-31T00:02:19",
    "latitude": 38.53831,
    "longitude": -90.25616,
    "speedOverGround": 0,
    "courseOverGround": 242.3,
    "heading": 511,
    "vesselName": "WENDY ANN",
    "imoNumber": "IMO0008171",
    "navigationStatus": "0"
  },
  {
    "vesselTrackingId": "368123060",
    "timestamp": "2022-03-31T00:02:11",
    "latitude": 29.93647,
    "longitude": -89.99179,
    "speedOverGround": 0,
    "courseOverGround": 102.4,
    "heading": 336,
    "vesselName": "KELSO",
    "imoNumber": "",
    "navigationStatus": "12"
  },
  {
    "vesselTrackingId": "367127110",
    "timestamp": "2022-03-31T00:02:21",
    "latitude": 29.78921,
    "longitude": -95.06353,
    "speedOverGround": 4.4,
    "courseOverGround": 211.3,
    "heading": 511,
    "vesselName": "CHERYL K",
    "imoNumber": "",
    "navigationStatus": "0"
  },
  {
    "vesselTrackingId": "538003242",
    "timestamp": "2022-03-31T00:02:21",
    "latitude": 29.94743,
    "longitude": -90.13949,
    "speedOverGround": 8.1,
    "courseOverGround": 343.4,
    "heading": 340,
    "vesselName": "VLAZAKIS I",
    "imoNumber": "IMO9546124",
    "navigationStatus": "0"
  },
  {
    "vesselTrackingId": "368115910",
    "timestamp": "2022-03-31T00:02:33",
    "latitude": 48.6683,
    "longitude": -123.4045,
    "speedOverGround": 0,
    "courseOverGround": 209.1,
    "heading": 154,
    "vesselName": "CASTAWAY",
    "imoNumber": "",
    "navigationStatus": "0"
  },
  {
    "vesselTrackingId": "257350000",
    "timestamp": "2022-03-31T00:02:25",
    "latitude": 49.30156,
    "longitude": -123.09478,
    "speedOverGround": 6.8,
    "courseOverGround": 98.8,
    "heading": 100,
    "vesselName": "STAR KILIMANJARO",
    "imoNumber": "IMO9396139",
    "navigationStatus": "0"
  },
  {
    "vesselTrackingId": "311061800",
    "timestamp": "2022-03-31T00:02:24",
    "latitude": 29.15103,
    "longitude": -89.25616,
    "speedOverGround": 11.1,
    "courseOverGround": 182.4,
    "heading": 181,
    "vesselName": "ELEKTRA",
    "imoNumber": "IMO9538153",
    "navigationStatus": "0"
  },
  {
    "vesselTrackingId": "367731170",
    "timestamp": "2022-03-31T00:01:37",
    "latitude": 49.29216,
    "longitude": -123.12787,
    "speedOverGround": 0,
    "courseOverGround": 360,
    "heading": 511,
    "vesselName": "PARAGON",
    "imoNumber": "",
    "navigationStatus": ""
  },
  {
    "vesselTrackingId": "367512930",
    "timestamp": "2022-03-31T00:02:47",
    "latitude": 37.04598,
    "longitude": -88.5398,
    "speedOverGround": 0,
    "courseOverGround": 206.1,
    "heading": 137,
    "vesselName": "ANGIE A",
    "imoNumber": "",
    "navigationStatus": "12"
  },
  {
    "vesselTrackingId": "338926404",
    "timestamp": "2022-03-31T00:02:48",
    "latitude": 24.56742,
    "longitude": -81.80092,
    "speedOverGround": 0,
    "courseOverGround": 219.8,
    "heading": 100,
    "vesselName": "CG ROBERT YERED",
    "imoNumber": "",
    "navigationStatus": "0"
  },
  {
    "vesselTrackingId": "319105900",
    "timestamp": "2022-03-31T00:03:05",
    "latitude": 25.93564,
    "longitude": -80.14816,
    "speedOverGround": 0.1,
    "courseOverGround": 318.2,
    "heading": 511,
    "vesselName": "MONICA",
    "imoNumber": "",
    "navigationStatus": ""
  },
  {
    "vesselTrackingId": "366693850",
    "timestamp": "2022-03-31T00:01:21",
    "latitude": 26.08246,
    "longitude": -80.11539,
    "speedOverGround": 0,
    "courseOverGround": 6.1,
    "heading": 81,
    "vesselName": "BROWARD",
    "imoNumber": "IMO9123568",
    "navigationStatus": "0"
  },
  {
    "vesselTrackingId": "367434610",
    "timestamp": "2022-03-31T00:01:25",
    "latitude": 40.60644,
    "longitude": -80.23594,
    "speedOverGround": 4.6,
    "courseOverGround": 5.9,
    "heading": 6,
    "vesselName": "D A GRIMM",
    "imoNumber": "",
    "navigationStatus": "0"
  },
  {
    "vesselTrackingId": "367932000",
    "timestamp": "2022-03-31T00:00:41",
    "latitude": 32.8609,
    "longitude": -79.95945,
    "speedOverGround": 0,
    "courseOverGround": 143,
    "heading": 281,
    "vesselName": "JOHN LENTHALL",
    "imoNumber": "IMO8325547",
    "navigationStatus": "5"
  },
  {
    "vesselTrackingId": "367627480",
    "timestamp": "2022-03-31T00:00:43",
    "latitude": 48.51891,
    "longitude": -122.62247,
    "speedOverGround": 0,
    "courseOverGround": 360,
    "heading": 511,
    "vesselName": "HONEY BADGER",
    "imoNumber": "",
    "navigationStatus": ""
  },
  {
    "vesselTrackingId": "374514000",
    "timestamp": "2022-03-31T00:01:36",
    "latitude": 29.99888,
    "longitude": -90.4431,
    "speedOverGround": 0.1,
    "courseOverGround": 220.7,
    "heading": 249,
    "vesselName": "AFRICAN SPOONBILL",
    "imoNumber": "IMO9701712",
    "navigationStatus": "1"
  },
  {
    "vesselTrackingId": "368239930",
    "timestamp": "2022-03-31T00:00:45",
    "latitude": 47.61641,
    "longitude": -122.51317,
    "speedOverGround": 0,
    "courseOverGround": 167.9,
    "heading": 511,
    "vesselName": "AMOREENA",
    "imoNumber": "IMO0000000",
    "navigationStatus": ""
  },
  {
    "vesselTrackingId": "367439590",
    "timestamp": "2022-03-31T00:01:38",
    "latitude": 21.31364,
    "longitude": -157.86668,
    "speedOverGround": 0.1,
    "courseOverGround": 28.8,
    "heading": 511,
    "vesselName": "PARADISE 2001",
    "imoNumber": "IMO8693009",
    "navigationStatus": ""
  },
  {
    "vesselTrackingId": "538071117",
    "timestamp": "2022-03-31T00:00:46",
    "latitude": 30.28044,
    "longitude": -87.67649,
    "speedOverGround": 0,
    "courseOverGround": 53.6,
    "heading": 511,
    "vesselName": "BREAKAWAY",
    "imoNumber": "",
    "navigationStatus": ""
  },
  {
    "vesselTrackingId": "368037750",
    "timestamp": "2022-03-31T00:01:38",
    "latitude": 26.27443,
    "longitude": -80.08054,
    "speedOverGround": 0.1,
    "courseOverGround": 171.2,
    "heading": 511,
    "vesselName": "WINGS SPREAD",
    "imoNumber": "",
    "navigationStatus": "15"
  },
  {
    "vesselTrackingId": "338196033",
    "timestamp": "2022-03-31T00:01:43",
    "latitude": 26.09286,
    "longitude": -80.17171,
    "speedOverGround": 0,
    "courseOverGround": 160.7,
    "heading": 511,
    "vesselName": "VALIANT EXPLORER",
    "imoNumber": "",
    "navigationStatus": ""
  },
  {
    "vesselTrackingId": "369970091",
    "timestamp": "2022-03-31T00:02:21",
    "latitude": 27.71551,
    "longitude": -80.10571,
    "speedOverGround": 10.7,
    "courseOverGround": 168,
    "heading": 168,
    "vesselName": "FERDINAND R HASSLER",
    "imoNumber": "IMO9478559",
    "navigationStatus": "0"
  },
  {
    "vesselTrackingId": "241075000",
    "timestamp": "2022-03-31T00:01:50",
    "latitude": 29.93926,
    "longitude": -90.3564,
    "speedOverGround": 0,
    "courseOverGround": 43.3,
    "heading": 289,
    "vesselName": "MAGDA P",
    "imoNumber": "IMO9476692",
    "navigationStatus": "5"
  },
  {
    "vesselTrackingId": "367717120",
    "timestamp": "2022-03-31T00:01:17",
    "latitude": 27.92823,
    "longitude": -82.42712,
    "speedOverGround": 0,
    "courseOverGround": 0,
    "heading": 511,
    "vesselName": "MASTER DAULTON",
    "imoNumber": "IMO8851675",
    "navigationStatus": "15"
  },
  {
    "vesselTrackingId": "368168150",
    "timestamp": "2022-03-31T00:02:03",
    "latitude": 40.27965,
    "longitude": -79.88191,
    "speedOverGround": 4.8,
    "courseOverGround": 44.9,
    "heading": 511,
    "vesselName": "ASHLEY MARIE",
    "imoNumber": "",
    "navigationStatus": "12"
  },
  {
    "vesselTrackingId": "311000452",
    "timestamp": "2022-03-31T00:01:18",
    "latitude": 29.46422,
    "longitude": -94.85065,
    "speedOverGround": 6,
    "courseOverGround": 157.2,
    "heading": 157,
    "vesselName": "SEOUL SPIRIT",
    "imoNumber": "IMO9248409",
    "navigationStatus": "8"
  },
  {
    "vesselTrackingId": "368034790",
    "timestamp": "2022-03-31T00:02:16",
    "latitude": 47.53775,
    "longitude": -122.32855,
    "speedOverGround": 0,
    "courseOverGround": 218.1,
    "heading": 133,
    "vesselName": "MARIE H",
    "imoNumber": "IMO7716969",
    "navigationStatus": "5"
  },
  {
    "vesselTrackingId": "367009420",
    "timestamp": "2022-03-31T00:01:18",
    "latitude": 41.51466,
    "longitude": -90.49793,
    "speedOverGround": 0,
    "courseOverGround": 286.6,
    "heading": 511,
    "vesselName": "JOLLY ROGER",
    "imoNumber": "",
    "navigationStatus": "0"
  },
  {
    "vesselTrackingId": "636014804",
    "timestamp": "2022-03-31T00:01:19",
    "latitude": 27.45999,
    "longitude": -94.68747,
    "speedOverGround": 1.2,
    "courseOverGround": 240.9,
    "heading": 235,
    "vesselName": "WORLD HARMONY",
    "imoNumber": "IMO9382970",
    "navigationStatus": "0"
  },
  {
    "vesselTrackingId": "367145440",
    "timestamp": "2022-03-31T00:01:26",
    "latitude": 30.28899,
    "longitude": -91.21729,
    "speedOverGround": 0,
    "courseOverGround": 360,
    "heading": 281,
    "vesselName": "KATIE GONSOULIN",
    "imoNumber": "",
    "navigationStatus": "15"
  },
  {
    "vesselTrackingId": "367430870",
    "timestamp": "2022-03-31T00:01:56",
    "latitude": 28.98022,
    "longitude": -89.37022,
    "speedOverGround": 0.1,
    "courseOverGround": 136.2,
    "heading": 511,
    "vesselName": "MISTER JUG",
    "imoNumber": "IMO8133310",
    "navigationStatus": ""
  },
  {
    "vesselTrackingId": "316047565",
    "timestamp": "2022-03-31T00:02:13",
    "latitude": 48.7427,
    "longitude": -123.34335,
    "speedOverGround": 16.3,
    "courseOverGround": 183.2,
    "heading": 183,
    "vesselName": "SEASPAN TRADER",
    "imoNumber": "IMO9886392",
    "navigationStatus": "0"
  },
  {
    "vesselTrackingId": "372148000",
    "timestamp": "2022-03-31T00:02:19",
    "latitude": 46.17563,
    "longitude": -123.20518,
    "speedOverGround": 12.9,
    "courseOverGround": 64,
    "heading": 63,
    "vesselName": "LONDON HIGHWAY",
    "imoNumber": "IMO9362267",
    "navigationStatus": "0"
  },
  {
    "vesselTrackingId": "368214170",
    "timestamp": "2022-03-31T00:02:20",
    "latitude": 27.81573,
    "longitude": -97.42197,
    "speedOverGround": 0,
    "courseOverGround": 294.6,
    "heading": 292,
    "vesselName": "BUD GOLDING",
    "imoNumber": "",
    "navigationStatus": "0"
  },
  {
    "vesselTrackingId": "316001252",
    "timestamp": "2022-03-31T00:02:21",
    "latitude": 48.76515,
    "longitude": -123.36152,
    "speedOverGround": 12.6,
    "courseOverGround": 29.9,
    "heading": 26,
    "vesselName": "QUEEN OF CUMBERLAND",
    "imoNumber": "IMO9009360",
    "navigationStatus": "0"
  },
  {
    "vesselTrackingId": "368198030",
    "timestamp": "2022-03-31T00:01:31",
    "latitude": 27.97622,
    "longitude": -82.82644,
    "speedOverGround": 0.1,
    "courseOverGround": 119.9,
    "heading": 511,
    "vesselName": "TICK TOCK",
    "imoNumber": "IMO0000000",
    "navigationStatus": ""
  },
  {
    "vesselTrackingId": "316041207",
    "timestamp": "2022-03-31T00:01:31",
    "latitude": 49.14893,
    "longitude": -123.69726,
    "speedOverGround": 0,
    "courseOverGround": 348,
    "heading": 511,
    "vesselName": "POLE DANCER",
    "imoNumber": "IMO0000000",
    "navigationStatus": ""
  }
]